Metadata-Version: 2.1
Name: django-queryset-constraint
Version: 1.0.4
Summary: A library for writing reliable data invariants in Django.
Home-page: https://github.com/magenta-aps/django_queryset_constraint
Author: Emil Madsen
Author-email: emil@magenta.dk
License: MPL-2.0
Download-URL: https://github.com/magenta-aps/django_queryset_constraint/archive/master.zip
Project-URL: Source, https://github.com/magenta-aps/django_queryset_constraint
Keywords: django
Platform: UNKNOWN
Classifier: Environment :: Web Environment
Classifier: Framework :: Django
Classifier: Framework :: Django :: 2.2
Classifier: Intended Audience :: Developers
Classifier: License :: OSI Approved
Classifier: License :: OSI Approved :: Mozilla Public License 2.0 (MPL 2.0)
Classifier: Operating System :: OS Independent
Classifier: Programming Language :: Python
Classifier: Programming Language :: Python :: 3
Classifier: Programming Language :: Python :: 3.6
Classifier: Programming Language :: Python :: 3.7
Classifier: Topic :: Internet :: WWW/HTTP
Classifier: Topic :: Internet :: WWW/HTTP :: Dynamic Content
Classifier: Topic :: Internet :: WWW/HTTP :: WSGI
Classifier: Topic :: Software Development :: Libraries :: Python Modules
Requires-Python: >=3.6
